[{"name": "WT-17260390686077633", "owner": "Administrator", "creation": "2024-09-11 14:17:48.598793", "modified": "2025-04-17 15:40:46.020244", "modified_by": "Administrator", "docstatus": 0, "idx": 37, "custom_name": "WT-17260390686077633", "template_name": "Trang web dịch vụ bảo vệ", "image_preview": "/files/cover_dvbv.png", "type_template": "Recruitment website", "link_download": "/files/ats_wt_17260390686077633.tar", "web_theme": null, "header_component": null, "footer_component": null, "template_in_use": 0, "installed_template": 0, "content": "<div class=\"ql-editor read-mode\"><p>Website dịch vụ bảo vệ</p></div>", "doctype": "MBW Website Template", "page_templates": [], "images": [{"name": "it107ite05", "owner": "Administrator", "creation": "2024-09-11 14:17:48.598793", "modified": "2025-04-17 15:27:06.695445", "modified_by": "Administrator", "docstatus": 0, "idx": 1, "image": "/files/preview_dvbv1.jpg", "parent": "WT-17260390686077633", "parentfield": "images", "parenttype": "MBW Website Template", "doctype": "MBW Website Template Preview Image"}, {"name": "it10cu6vaj", "owner": "Administrator", "creation": "2024-09-11 14:17:48.598793", "modified": "2025-04-17 15:27:06.695445", "modified_by": "Administrator", "docstatus": 0, "idx": 2, "image": "/files/preview_dvbv2.jpg", "parent": "WT-17260390686077633", "parentfield": "images", "parenttype": "MBW Website Template", "doctype": "MBW Website Template Preview Image"}]}, {"name": "WT-17235991837942781", "owner": "Administrator", "creation": "2024-08-14 08:33:03.783676", "modified": "2025-04-17 15:30:39.387258", "modified_by": "Administrator", "docstatus": 0, "idx": 65, "custom_name": "WT-17235991837942781", "template_name": "Trang web tuyển dụng", "image_preview": "/files/cover_tuyendung.png", "type_template": "Recruitment website", "link_download": "/files/ats_wt_17235991837942781.tar", "web_theme": null, "header_component": null, "footer_component": null, "template_in_use": 0, "installed_template": 0, "content": "<div class=\"ql-editor read-mode\"><p>website tuyển dụng</p></div>", "doctype": "MBW Website Template", "page_templates": [], "images": [{"name": "it10gfdn11", "owner": "Administrator", "creation": "2024-08-14 08:33:03.783676", "modified": "2025-04-17 15:25:10.002373", "modified_by": "Administrator", "docstatus": 0, "idx": 1, "image": "/files/preview_tuyendung1.jpg", "parent": "WT-17235991837942781", "parentfield": "images", "parenttype": "MBW Website Template", "doctype": "MBW Website Template Preview Image"}, {"name": "it10tdc0dn", "owner": "Administrator", "creation": "2024-08-14 08:33:03.783676", "modified": "2025-04-17 15:25:10.002373", "modified_by": "Administrator", "docstatus": 0, "idx": 2, "image": "/files/preview_tuyendung2.jpg", "parent": "WT-17235991837942781", "parentfield": "images", "parenttype": "MBW Website Template", "doctype": "MBW Website Template Preview Image"}]}, {"name": "WT-17267305975035124", "owner": "Administrator", "creation": "2024-09-19 14:23:17.482868", "modified": "2025-04-16 14:12:41.732327", "modified_by": "Administrator", "docstatus": 0, "idx": 16, "custom_name": "WT-17267305975035124", "template_name": "Trang web tư vấn du học", "image_preview": "/files/cover_tvdh.png", "type_template": "Introduction website", "link_download": "/files/wt_17267305975035124.tar", "template_in_use": 0, "installed_template": 0, "content": "<div class=\"ql-editor read-mode\"><p>Website tư vấn du học</p></div>", "doctype": "MBW Website Template", "page_templates": [], "images": [{"name": "it114hc1t2", "owner": "Administrator", "creation": "2024-09-19 14:23:17.482868", "modified": "2025-04-16 14:12:41.732327", "modified_by": "Administrator", "docstatus": 0, "idx": 1, "image": "/files/preview1_tvdh.jpg", "parent": "WT-17267305975035124", "parentfield": "images", "parenttype": "MBW Website Template", "doctype": "MBW Website Template Preview Image"}, {"name": "it11e2llrr", "owner": "Administrator", "creation": "2024-09-19 14:23:17.482868", "modified": "2025-04-16 14:12:41.732327", "modified_by": "Administrator", "docstatus": 0, "idx": 2, "image": "/files/preview2_tvdh.jpg", "parent": "WT-17267305975035124", "parentfield": "images", "parenttype": "MBW Website Template", "doctype": "MBW Website Template Preview Image"}], "web_theme": null, "header_component": null, "footer_component": null}, {"name": "WT-17256067498788319", "owner": "Administrator", "creation": "2024-09-06 14:12:29.873041", "modified": "2025-04-16 14:12:41.726614", "modified_by": "Administrator", "docstatus": 0, "idx": 25, "custom_name": "WT-17256067498788319", "template_name": "Trang web dịch vụ vệ sinh", "image_preview": "/files/cover_dvvs.png", "type_template": "Introduction website", "link_download": "/files/wt_17256067498788319.tar", "template_in_use": 0, "installed_template": 0, "content": "<div class=\"ql-editor read-mode\"><p>Trang dịch vụ</p></div>", "doctype": "MBW Website Template", "page_templates": [], "images": [{"name": "it11spmah0", "owner": "Administrator", "creation": "2024-09-06 14:12:29.873041", "modified": "2025-04-16 14:12:41.726614", "modified_by": "Administrator", "docstatus": 0, "idx": 1, "image": "/files/preview_dvvs1.jpg", "parent": "WT-17256067498788319", "parentfield": "images", "parenttype": "MBW Website Template", "doctype": "MBW Website Template Preview Image"}, {"name": "it11ibdlc2", "owner": "Administrator", "creation": "2024-09-06 14:12:29.873041", "modified": "2025-04-16 14:12:41.726614", "modified_by": "Administrator", "docstatus": 0, "idx": 2, "image": "/files/preview_dvvs2.jpg", "parent": "WT-17256067498788319", "parentfield": "images", "parenttype": "MBW Website Template", "doctype": "MBW Website Template Preview Image"}], "web_theme": null, "header_component": null, "footer_component": null}, {"name": "WT-17244758376986880", "owner": "Administrator", "creation": "2024-08-24 12:03:57.683037", "modified": "2025-04-16 14:12:41.720967", "modified_by": "Administrator", "docstatus": 0, "idx": 39, "custom_name": "WT-17244758376986880", "template_name": "Trang web spa", "image_preview": "/files/cover_spa.png", "type_template": "Introduction website", "link_download": "/files/wt_17244758376986880.tar", "template_in_use": 0, "installed_template": 0, "content": "<div class=\"ql-editor read-mode\"><p>web spa </p></div>", "doctype": "MBW Website Template", "page_templates": [], "images": [{"name": "it113itl9l", "owner": "Administrator", "creation": "2024-08-24 12:03:57.683037", "modified": "2025-04-16 14:12:41.720967", "modified_by": "Administrator", "docstatus": 0, "idx": 1, "image": "/files/preview_spa1.jpg", "parent": "WT-17244758376986880", "parentfield": "images", "parenttype": "MBW Website Template", "doctype": "MBW Website Template Preview Image"}, {"name": "it1176muje", "owner": "Administrator", "creation": "2024-08-24 12:03:57.683037", "modified": "2025-04-16 14:12:41.720967", "modified_by": "Administrator", "docstatus": 0, "idx": 2, "image": "/files/preview_spa2.jpg", "parent": "WT-17244758376986880", "parentfield": "images", "parenttype": "MBW Website Template", "doctype": "MBW Website Template Preview Image"}], "web_theme": null, "header_component": null, "footer_component": null}, {"name": "WT-17261307021784525", "owner": "Administrator", "creation": "2024-09-12 15:45:02.176334", "modified": "2025-04-16 14:12:41.715640", "modified_by": "Administrator", "docstatus": 0, "idx": 15, "custom_name": "WT-17261307021784525", "template_name": "Trang web chăm sóc sức khỏe", "image_preview": "/files/cover_cssk.png", "type_template": "Introduction website", "link_download": "/files/wt_17261307021784525.tar", "template_in_use": 0, "installed_template": 0, "doctype": "MBW Website Template", "page_templates": [], "images": [{"name": "it11csvr72", "owner": "Administrator", "creation": "2024-09-12 15:45:02.176334", "modified": "2025-04-16 14:12:41.715640", "modified_by": "Administrator", "docstatus": 0, "idx": 1, "image": "/files/preview_cssk1.jpg", "parent": "WT-17261307021784525", "parentfield": "images", "parenttype": "MBW Website Template", "doctype": "MBW Website Template Preview Image"}, {"name": "it11al45ce", "owner": "Administrator", "creation": "2024-09-12 15:45:02.176334", "modified": "2025-04-16 14:12:41.715640", "modified_by": "Administrator", "docstatus": 0, "idx": 2, "image": "/files/preview_cssk2.jpg", "parent": "WT-17261307021784525", "parentfield": "images", "parenttype": "MBW Website Template", "doctype": "MBW Website Template Preview Image"}], "web_theme": null, "header_component": null, "footer_component": null}, {"name": "WT-17228486843340792", "owner": "Administrator", "creation": "2024-04-26 11:45:56.722371", "modified": "2025-04-16 14:12:41.709989", "modified_by": "Administrator", "docstatus": 0, "idx": 32, "custom_name": "WT-17228486843340792", "template_name": "Trang web kế toán", "image_preview": "/files/cover.png", "type_template": "Introduction website", "link_download": "/files/wt_17228486843340792.tar", "template_in_use": 0, "installed_template": 0, "content": "<div class=\"ql-editor read-mode\"><h2><strong style=\"font-size: 24px;\">Tính năng nổi bật</strong></h2><p><strong style=\"font-size: 14px;\">1. Theme được tối ưu điểm Google Speed:</strong></p><p><span style=\"font-size: 14px;\"> Theme được xây dựng tối ưu hoá css,js, tối ưu code, sử dụng Cache và Preload giúp website load nhanh và đúng tiêu chuẩn của Google Speed đề ra và hỗ trợ SEO tốt cho website.</span></p><p><strong style=\"font-size: 14px;\">2. Lazy load:</strong><span style=\"font-size: 14px;\">&nbsp;ảnh toàn bộ trang được sử dụng công nghệ lazy load, đảm bảo ảnh hiển thị rõ nét nhưng không ảnh hưởng đến tốc độ website.</span></p><p><strong style=\"font-size: 14px;\">3. Flash sale trang chủ</strong></p></div>", "doctype": "MBW Website Template", "page_templates": [], "images": [{"name": "it1159pmu3", "owner": "Administrator", "creation": "2024-04-26 11:45:56.722371", "modified": "2025-04-16 14:12:41.709989", "modified_by": "Administrator", "docstatus": 0, "idx": 1, "image": "/files/preview.jpg", "parent": "WT-17228486843340792", "parentfield": "images", "parenttype": "MBW Website Template", "doctype": "MBW Website Template Preview Image"}, {"name": "it110jf79s", "owner": "Administrator", "creation": "2024-04-26 11:45:56.722371", "modified": "2025-04-16 14:12:41.709989", "modified_by": "Administrator", "docstatus": 0, "idx": 2, "image": "/files/preview (1).jpg", "parent": "WT-17228486843340792", "parentfield": "images", "parenttype": "MBW Website Template", "doctype": "MBW Website Template Preview Image"}], "web_theme": null, "header_component": null, "footer_component": null}, {"name": "WT-17242341044285330", "owner": "Administrator", "creation": "2024-08-21 16:55:04.422685", "modified": "2025-04-16 14:12:41.704285", "modified_by": "Administrator", "docstatus": 0, "idx": 55, "custom_name": "WT-17242341044285330", "template_name": "Trang web nội thất", "image_preview": "/files/cover_noi_that.png", "type_template": "Sales and recruitment website with contact-based ordering", "link_download": "/files/wt_17242341044285330.tar", "template_in_use": 0, "installed_template": 0, "content": "<div class=\"ql-editor read-mode\"><p>Trang web nội thất</p></div>", "doctype": "MBW Website Template", "page_templates": [], "images": [{"name": "it11uf6j0s", "owner": "Administrator", "creation": "2024-08-21 16:55:04.422685", "modified": "2025-04-16 14:12:41.704285", "modified_by": "Administrator", "docstatus": 0, "idx": 1, "image": "/files/preview_noi_that_1.jpg", "parent": "WT-17242341044285330", "parentfield": "images", "parenttype": "MBW Website Template", "doctype": "MBW Website Template Preview Image"}, {"name": "it11mtsb3r", "owner": "Administrator", "creation": "2024-08-21 16:55:04.422685", "modified": "2025-04-16 14:12:41.704285", "modified_by": "Administrator", "docstatus": 0, "idx": 2, "image": "/files/preview_noi_that_2.jpg", "parent": "WT-17242341044285330", "parentfield": "images", "parenttype": "MBW Website Template", "doctype": "MBW Website Template Preview Image"}], "web_theme": null, "header_component": null, "footer_component": null}, {"name": "WT-17249202482992115", "owner": "Administrator", "creation": "2024-08-29 15:30:48.290043", "modified": "2025-04-16 14:12:41.698576", "modified_by": "Administrator", "docstatus": 0, "idx": 41, "custom_name": "WT-17249202482992115", "template_name": "Trang web xây dựng", "image_preview": "/files/cover_xay_dung.png", "type_template": "Sales website with contact-based ordering", "link_download": "/files/wt_17249202482992115.tar", "template_in_use": 0, "installed_template": 0, "content": "<div class=\"ql-editor read-mode\"><p>Web xây dựng</p></div>", "doctype": "MBW Website Template", "page_templates": [], "images": [{"name": "it10hr31l7", "owner": "Administrator", "creation": "2024-08-29 15:30:48.290043", "modified": "2025-04-16 14:12:41.698576", "modified_by": "Administrator", "docstatus": 0, "idx": 1, "image": "/files/preview_xaydung1.jpg", "parent": "WT-17249202482992115", "parentfield": "images", "parenttype": "MBW Website Template", "doctype": "MBW Website Template Preview Image"}, {"name": "it10quj9hv", "owner": "Administrator", "creation": "2024-08-29 15:30:48.290043", "modified": "2025-04-16 14:12:41.698576", "modified_by": "Administrator", "docstatus": 0, "idx": 2, "image": "/files/preview_xaydung2.jpg", "parent": "WT-17249202482992115", "parentfield": "images", "parenttype": "MBW Website Template", "doctype": "MBW Website Template Preview Image"}], "web_theme": null, "header_component": null, "footer_component": null}, {"name": "WT-17280939384892652", "owner": "Administrator", "creation": "2024-10-05 09:05:38.474780", "modified": "2025-04-16 14:12:41.692138", "modified_by": "Administrator", "docstatus": 0, "idx": 48, "custom_name": "WT-17280939384892652", "template_name": "Trang web bán hàng trái cây", "image_preview": "/files/cover2d4745.png", "type_template": "Sales website with shopping cart", "link_download": "/files/wt_17280939384892652.tar", "template_in_use": 0, "installed_template": 0, "content": "<div class=\"ql-editor read-mode\"><p>Website bán hàng trái cây</p></div>", "doctype": "MBW Website Template", "page_templates": [], "images": [{"name": "it10g3gtnq", "owner": "Administrator", "creation": "2024-10-05 09:05:38.474780", "modified": "2025-04-16 14:12:41.692138", "modified_by": "Administrator", "docstatus": 0, "idx": 1, "image": "/files/previewc0db4c.jpg", "parent": "WT-17280939384892652", "parentfield": "images", "parenttype": "MBW Website Template", "doctype": "MBW Website Template Preview Image"}, {"name": "it108t9f3h", "owner": "Administrator", "creation": "2024-10-05 09:05:38.474780", "modified": "2025-04-16 14:12:41.692138", "modified_by": "Administrator", "docstatus": 0, "idx": 2, "image": "/files/preview (1)ea9e8c.jpg", "parent": "WT-17280939384892652", "parentfield": "images", "parenttype": "MBW Website Template", "doctype": "MBW Website Template Preview Image"}, {"name": "it10i36vdd", "owner": "Administrator", "creation": "2024-10-05 09:05:38.474780", "modified": "2025-04-16 14:12:41.692138", "modified_by": "Administrator", "docstatus": 0, "idx": 3, "image": "/files/preview (2).jpg", "parent": "WT-17280939384892652", "parentfield": "images", "parenttype": "MBW Website Template", "doctype": "MBW Website Template Preview Image"}, {"name": "it10bvlopd", "owner": "Administrator", "creation": "2024-10-05 09:05:38.474780", "modified": "2025-04-16 14:12:41.692138", "modified_by": "Administrator", "docstatus": 0, "idx": 4, "image": "/files/preview (3).jpg", "parent": "WT-17280939384892652", "parentfield": "images", "parenttype": "MBW Website Template", "doctype": "MBW Website Template Preview Image"}], "web_theme": null, "header_component": null, "footer_component": null}]